<?xml version="1.0"?>
<ArrayOfUser xmlns:xsi="http://www.w3.org/2001/XMLSchema-instance" xmlns:xsd="http://www.w3.org/2001/XMLSchema">
  <User>
    <_Login>Log</_Login>
    <_Password>Pass</_Password>
    <BirthDay>2011-05-12T00:00:00</BirthDay>
    <MathScore>0</MathScore>
    <GeographyScore>0</GeographyScore>
    <EnglishScore>0</EnglishScore>
    <MixtureScore>0</MixtureScore>
  </User>
  <User>
    <_Login>Log</_Login>
    <_Password>Pass</_Password>
    <BirthDay>2000-04-17T00:00:00</BirthDay>
    <MathScore>0</MathScore>
    <GeographyScore>0</GeographyScore>
    <EnglishScore>0</EnglishScore>
    <MixtureScore>0</MixtureScore>
  </User>
  <User>
    <_Login>Log</_Login>
    <_Password>Pass</_Password>
    <BirthDay>2000-04-29T00:00:00</BirthDay>
    <MathScore>0</MathScore>
    <GeographyScore>0</GeographyScore>
    <EnglishScore>0</EnglishScore>
    <MixtureScore>0</MixtureScore>
  </User>
  <User>
    <_Login>Log</_Login>
    <_Password>Pass</_Password>
    <BirthDay>2001-01-01T00:00:00</BirthDay>
    <MathScore>0</MathScore>
    <GeographyScore>0</GeographyScore>
    <EnglishScore>0</EnglishScore>
    <MixtureScore>0</MixtureScore>
  </User>
  <User>
    <_Login>Log</_Login>
    <_Password>Pass</_Password>
    <BirthDay>2000-05-15T00:00:00</BirthDay>
    <MathScore>0</MathScore>
    <GeographyScore>0</GeographyScore>
    <EnglishScore>0</EnglishScore>
    <MixtureScore>0</MixtureScore>
  </User>
  <User>
    <_Login>Log</_Login>
    <_Password>Pass</_Password>
    <BirthDay>2000-02-14T00:00:00</BirthDay>
    <MathScore>0</MathScore>
    <GeographyScore>0</GeographyScore>
    <EnglishScore>0</EnglishScore>
    <MixtureScore>0</MixtureScore>
  </User>
  <User>
    <_Login>Log</_Login>
    <_Password>Pass</_Password>
    <BirthDay>2001-01-01T00:00:00</BirthDay>
    <MathScore>0</MathScore>
    <GeographyScore>0</GeographyScore>
    <EnglishScore>0</EnglishScore>
    <MixtureScore>0</MixtureScore>
  </User>
  <User>
    <_Login>Log</_Login>
    <_Password>Pass</_Password>
    <BirthDay>1989-02-05T00:00:00</BirthDay>
    <MathScore>0</MathScore>
    <GeographyScore>0</GeographyScore>
    <EnglishScore>0</EnglishScore>
    <MixtureScore>0</MixtureScore>
  </User>
  <User>
    <_Login>Log</_Login>
    <_Password>Pass</_Password>
    <BirthDay>1974-03-12T00:00:00</BirthDay>
    <MathScore>0</MathScore>
    <GeographyScore>0</GeographyScore>
    <EnglishScore>0</EnglishScore>
    <MixtureScore>0</MixtureScore>
  </User>
  <User>
    <_Login>Log</_Login>
    <_Password>Pass</_Password>
    <BirthDay>2012-12-12T00:00:00</BirthDay>
    <MathScore>0</MathScore>
    <GeographyScore>0</GeographyScore>
    <EnglishScore>0</EnglishScore>
    <MixtureScore>0</MixtureScore>
  </User>
  <User>
    <_Login>Log</_Login>
    <_Password>Pass</_Password>
    <BirthDay>2000-12-12T00:00:00</BirthDay>
    <MathScore>0</MathScore>
    <GeographyScore>0</GeographyScore>
    <EnglishScore>0</EnglishScore>
    <MixtureScore>0</MixtureScore>
  </User>
  <User>
    <_Login>Log</_Login>
    <_Password>Pass</_Password>
    <BirthDay>2002-02-02T00:00:00</BirthDay>
    <MathScore>0</MathScore>
    <GeographyScore>0</GeographyScore>
    <EnglishScore>0</EnglishScore>
    <MixtureScore>0</MixtureScore>
  </User>
  <User>
    <_Login>Log</_Login>
    <_Password>Pass</_Password>
    <BirthDay>2000-10-20T00:00:00</BirthDay>
    <MathScore>0</MathScore>
    <GeographyScore>0</GeographyScore>
    <EnglishScore>0</EnglishScore>
    <MixtureScore>0</MixtureScore>
  </User>
  <User>
    <_Login>Log</_Login>
    <_Password>Pass</_Password>
    <BirthDay>2010-10-20T00:00:00</BirthDay>
    <MathScore>0</MathScore>
    <GeographyScore>0</GeographyScore>
    <EnglishScore>0</EnglishScore>
    <MixtureScore>0</MixtureScore>
  </User>
  <User>
    <_Login>a</_Login>
    <_Password>a</_Password>
    <BirthDay>2000-10-20T00:00:00</BirthDay>
    <MathScore>19</MathScore>
    <GeographyScore>20</GeographyScore>
    <EnglishScore>0</EnglishScore>
    <MixtureScore>0</MixtureScore>
  </User>
  <User>
    <_Login>qe</_Login>
    <_Password>qe</_Password>
    <BirthDay>2000-12-12T00:00:00</BirthDay>
    <MathScore>0</MathScore>
    <GeographyScore>0</GeographyScore>
    <EnglishScore>0</EnglishScore>
    <MixtureScore>0</MixtureScore>
  </User>
  <User>
    <_Login>qr</_Login>
    <_Password>2004</_Password>
    <BirthDay>2000-12-12T00:00:00</BirthDay>
    <MathScore>0</MathScore>
    <GeographyScore>0</GeographyScore>
    <EnglishScore>0</EnglishScore>
    <MixtureScore>0</MixtureScore>
  </User>
  <User>
    <_Login>kam</_Login>
    <_Password>kam</_Password>
    <BirthDay>2000-12-14T00:00:00</BirthDay>
    <MathScore>4</MathScore>
    <GeographyScore>0</GeographyScore>
    <EnglishScore>0</EnglishScore>
    <MixtureScore>0</MixtureScore>
  </User>
  <User>
    <_Login>b</_Login>
    <_Password>b</_Password>
    <BirthDay>2001-12-12T00:00:00</BirthDay>
    <MathScore>6</MathScore>
    <GeographyScore>0</GeographyScore>
    <EnglishScore>0</EnglishScore>
    <MixtureScore>0</MixtureScore>
  </User>
</ArrayOfUser>